nornir_ipfabric/__init__.py
nornir_ipfabric/plugins/__init__.py
nornir_ipfabric/plugins/inventory/__init__.py
nornir_ipfabric/plugins/inventory/ipfabric.py
nornir_ipfabric-0.1.4.dist-info/LICENSE
nornir_ipfabric-0.1.4.dist-info/METADATA
nornir_ipfabric-0.1.4.dist-info/WHEEL
nornir_ipfabric-0.1.4.dist-info/entry_points.txt
nornir_ipfabric-0.1.4.dist-info/top_level.txt
nornir_ipfabric-0.1.4.dist-info/RECORD
