Metadata-Version: 2.1
Name: nornir-ipfabric
Version: 0.1.4
Summary: nornir_ipfabric plugin for nornir
Home-page: https://github.com/routetonull/nornir_ipfabric
Author: Gian Paolo Boarina
Author-email: gp.boarina@gmail.com
License: Apache License, Version 2.0
Keywords: nornir ipfabric automation
Platform: any
Classifier: Development Status :: 3 - Alpha
Classifier: Topic :: System :: Networking
Classifier: License :: OSI Approved :: Apache Software License
Classifier: Programming Language :: Python :: 3
Classifier: Programming Language :: Python :: 3.6
Classifier: Programming Language :: Python :: 3.7
Classifier: Programming Language :: Python :: 3.8
Classifier: Programming Language :: Python :: 3.9
Requires-Python: >=3.6
Requires-Dist: nornir (<4.0.0,>=3.0.0a4)
Requires-Dist: simplejson (==3.17.2)
Requires-Dist: urllib3 (==1.25.11)
Requires-Dist: requests (>=2.24.0)
